hptpy/__init__.py
hptpy/anova.py
hptpy/t_tests.py
hptpy/midcal/__init__.py
hptpy/midcal/midcal_anova.py
hptpy/midcal/midcal_ttest.py
hptpy-0.0.8.dist-info/LICENSE
hptpy-0.0.8.dist-info/METADATA
hptpy-0.0.8.dist-info/WHEEL
hptpy-0.0.8.dist-info/top_level.txt
hptpy-0.0.8.dist-info/RECORD
