Metadata-Version: 2.1
Name: hptpy
Version: 0.0.8
Summary: Hypothesis Testing Python Library
Home-page: https://github.com/alperenbalik/hptpy
Author: Alperen Balık
Author-email: alperenbalik@outlook.com
License: UNKNOWN
Platform: UNKNOWN
Requires-Dist: scipy (>=0.9.0)
Requires-Dist: numpy (==1.15.4)
Requires-Dist: statsmodels (>=0.9.0)
